MANIFEST.in
README.md
setup.py
HIIregs/__init__.py
HIIregs/temden/curve_SII_ratio_vs_Ne_density.dat
HIIregs/temden/curve_SII_ratio_vs_Ne_density_temden_output.dat
astroismlib.egg-info/PKG-INFO
astroismlib.egg-info/SOURCES.txt
astroismlib.egg-info/dependency_links.txt
astroismlib.egg-info/top_level.txt
examples/Ha_ew.fits
examples/Ha_flux_ext.fits
examples/Hb_flux_ext.fits
examples/NII_flux_ext.fits
examples/OIII_flux_ext.fits
examples/example_grids_models.ipynb
examples/fig_diag_bpt.png
examples/fig_diag_whan.png
examples/mask_bpt.fits
examples/mask_diag.fits
examples/mask_whan.fits
extinction/__init__.py
metallicity/__init__.py
model_ionization/__init__.py
model_ionization/models_phot/Peg_cont_n10/README
model_ionization/models_phot/Peg_cont_n10/descompress.sh
model_ionization/models_phot/Peg_cont_n10/phapn_Z0.1_4Myr_q1.0e7.ph4
model_ionization/models_phot/Peg_cont_n10/phapn_Z0.1_4Myr_q1.5e8.ph4
model_ionization/models_phot/Peg_cont_n10/phapn_Z0.1_4Myr_q2.0e7.ph4
model_ionization/models_phot/Peg_cont_n10/phapn_Z0.1_4Myr_q3.0e8.ph4
model_ionization/models_phot/Peg_cont_n10/phapn_Z0.1_4Myr_q4.0e7.ph4
model_ionization/models_phot/Peg_cont_n10/phapn_Z0.1_4Myr_q5.0e6.ph4
model_ionization/models_phot/Peg_cont_n10/phapn_Z0.1_4Myr_q8.0e7.ph4
model_ionization/models_phot/Peg_cont_n10/phapn_Z0.2_4Myr_q1.0e7.ph4
model_ionization/models_phot/Peg_cont_n10/phapn_Z0.2_4Myr_q1.5e8.ph4
model_ionization/models_phot/Peg_cont_n10/phapn_Z0.2_4Myr_q2.0e7.ph4
model_ionization/models_phot/Peg_cont_n10/phapn_Z0.2_4Myr_q3.0e8.ph4
model_ionization/models_phot/Peg_cont_n10/phapn_Z0.2_4Myr_q4.0e7.ph4
model_ionization/models_phot/Peg_cont_n10/phapn_Z0.2_4Myr_q5.0e6.ph4
model_ionization/models_phot/Peg_cont_n10/phapn_Z0.2_4Myr_q8.0e7.ph4
model_ionization/models_phot/Peg_cont_n10/phapn_Z0.5_4Myr_q1.0e7.ph4
model_ionization/models_phot/Peg_cont_n10/phapn_Z0.5_4Myr_q1.5e8.ph4
model_ionization/models_phot/Peg_cont_n10/phapn_Z0.5_4Myr_q2.0e7.ph4
model_ionization/models_phot/Peg_cont_n10/phapn_Z0.5_4Myr_q3.0e8.ph4
model_ionization/models_phot/Peg_cont_n10/phapn_Z0.5_4Myr_q4.0e7.ph4
