Metadata-Version: 2.1
Name: astroismlib
Version: 1.1.0
Summary: Utilities to handle models of shock and ionization
Home-page: https://gitlab.com/joseaher/astroismlib
Author: J. A. Hernandez-Jimenez
Author-email: joseaher@gmail.com
